{
    "description": "变电站巡视检测",
    "engine_id": "TransStationPatrolDete",
    "server_id": "trans_station_patrol_server",
    "concurrency": 2,
    "confidence_threshold": 0.45,
    "engine_type": "ENGINE_DETECTOR",
    "task_type": "DETECT",
    "infer_device": "GPU:0",
    "input_size": "768X768",
    "labelfile": "./model/labels/trans_station_patrol_dete_v24.01.01.txt",
    "labeloffset": 0,
    "max_batch_size": 4,
    "model_nms": "class",
    "type_resizer": "padded",
    "modelfile": "./model/trans_station_patrol_dete_v24.01.01.m",
    "modeltype": "TYPE_TENSORRT",
    "nbclasses": 10,
    "nms_threshold": 0.5,
    "objectType": -1,
    "outclass": "0:10095;1:10096;2:10097;3:10098;4:10099;5:100100;6:100101;7:100102;8:100103;9:100104",
    "output_blobs_names": "prob",
    "scale_values": "0.003922;0.003922;0.003922",
    "swapBR": true,
    "type_nms": "Union",
    "type_result_cvter": "Yolo",
    "src_model_file": "trans_station_patrol_dete_v24.01.01_dynamic.onnx",
    "trt_model_file": "trans_station_patrol_dete_v24.01.01.trt7",
    "m_model_file": "trans_station_patrol_dete_v24.01.01.m",
    "precision": 1,
    "suffix": "-transtation -d"
}